riemannian_manifold/__init__.py
riemannian_manifold/riemannian_manifold.py
riemann_manifold-0.3.dist-info/LICENSE
riemann_manifold-0.3.dist-info/METADATA
riemann_manifold-0.3.dist-info/WHEEL
riemann_manifold-0.3.dist-info/top_level.txt
riemann_manifold-0.3.dist-info/RECORD
