Metadata-Version: 2.1
Name: riemann-manifold
Version: 0.3
Summary: A package for working with Riemannian manifolds in Python
Home-page: https://github.com/swittum/riemannian_manifold
Author: Simon Wittum
Author-email: simonwittum@gmx.de
Classifier: Programming Language :: Python :: 3
Classifier: License :: OSI Approved :: MIT License
Classifier: Operating System :: OS Independent
License-File: LICENSE
Requires-Dist: numpy (==1.26.4)
Requires-Dist: scipy (==1.12.0)
Requires-Dist: sympy (==1.12)
